lions_410e_midyear_2023_common/__init__.py
lions_410e_midyear_2023_common/build_pdf.py
lions_410e_midyear_2023_common/constants.py
lions_410e_midyear_2023_common/data.json
lions_410e_midyear_2023_common/emailer.py
lions_410e_midyear_2023_common/models.py
lions_410e_midyear_2023_common/sqs.py
lions_410e_midyear_2023_common/test.pdf
lions_410e_midyear_2023_common/test.py
lions_410e_midyear_2023_common-1.3.0.dist-info/METADATA
lions_410e_midyear_2023_common-1.3.0.dist-info/WHEEL
lions_410e_midyear_2023_common-1.3.0.dist-info/RECORD
