Metadata-Version: 2.1
Name: lions-410e-midyear-2023-common
Version: 1.3.0
Summary: Common libraries for applications related to the 2023 Lions District 410E Midyear Conference
Home-page: https://gitlab.com/410e-midyear-2023/common
Author: Kim van Wyk
Author-email: vanwykk@gmail.com
Requires-Python: >=3.7,<4.0
Classifier: Programming Language :: Python :: 3
Classifier: Programming Language :: Python :: 3.7
Classifier: Programming Language :: Python :: 3.8
Classifier: Programming Language :: Python :: 3.9
Classifier: Programming Language :: Python :: 3.10
Classifier: Programming Language :: Python :: 3.11
Requires-Dist: boto3 (>=1.20.3,<2.0.0)
Requires-Dist: click (>=8.0.3,<9.0.0)
Requires-Dist: docker (>=5.0.3,<6.0.0)
Requires-Dist: filetype (>=1.0.13,<2.0.0)
Requires-Dist: pydantic (>=1.8.2,<2.0.0)
Requires-Dist: python-dotenv (>=0.19.2,<0.20.0)
Requires-Dist: rich (>=11.0.0,<12.0.0)
Requires-Dist: sendgrid (>=6.9.7,<7.0.0)
Project-URL: Repository, https://gitlab.com/410e-midyear-2023/common
